start_code/__init__.py
start_code-0.0.1.dist-info/WHEEL
start_code-0.0.1.dist-info/METADATA
start_code-0.0.1.dist-info/RECORD
