Metadata-Version: 2.1
Name: start-code
Version: 0.0.1
Summary: Boilerplate Python Code
Author: Marcelino G. Veloso III
Author-email: mars@veloso.one
Requires-Python: >=3.10,<4.0
Classifier: Programming Language :: Python :: 3
Classifier: Programming Language :: Python :: 3.10
Classifier: Programming Language :: Python :: 3.11
Requires-Dist: python-dotenv (>=0.21,<0.22)
